tinywin/__init__.py
tinywin/core.py
tinywin/helpers.py
tinywin/panes.py
tinywin/screen.py
tinywin-0.2.5.dist-info/LICENSE
tinywin-0.2.5.dist-info/METADATA
tinywin-0.2.5.dist-info/WHEEL
tinywin-0.2.5.dist-info/top_level.txt
tinywin-0.2.5.dist-info/RECORD
