Metadata-Version: 2.1
Name: tinywin
Version: 0.2.5
Summary: A tiny Curses window management library.
Home-page: https://github.com/knicholson32/tinywin/
Author: Keenan Nicholson
Author-email: 
License: UNKNOWN
Platform: UNKNOWN
Classifier: Programming Language :: Python :: 3.6
Classifier: License :: OSI Approved :: MIT License
Classifier: Operating System :: Unix
Classifier: Environment :: Console :: Curses
